pynxtools_igor/__init__.py
pynxtools_igor/mkdocs.py
pynxtools_igor/reader.py
pynxtools_igor/nomad/entrypoints.py
pynxtools_igor/nomad/examples/Conversion example.ipynb
pynxtools_igor/nomad/examples/Conversion of time-resolved x-ray diffraction data.ipynb
pynxtools_igor/nomad/examples/Fig2a.pxp
pynxtools_igor/nomad/examples/Fig2b.pxp
pynxtools_igor/nomad/examples/Fig2c.pxp
pynxtools_igor/nomad/examples/Fig2d.pxp
pynxtools_igor/nomad/examples/Fig3a.pxp
pynxtools_igor/nomad/examples/Fig7a.pxp
pynxtools_igor/nomad/examples/Fig7b.pxp
pynxtools_igor/nomad/examples/Fig7c.pxp
pynxtools_igor/nomad/examples/Norm_0057.ibw
pynxtools_igor/nomad/examples/Norm_0059.ibw
pynxtools_igor/nomad/examples/README.md
pynxtools_igor/nomad/examples/config_file.json
pynxtools_igor/nomad/examples/config_file_delay_scans.json
pynxtools_igor/nomad/examples/config_file_energies.json
pynxtools_igor/nomad/examples/config_file_peaks.json
pynxtools_igor/nomad/examples/config_file_temperatures.json
pynxtools_igor-0.1.4.dist-info/licenses/LICENSE
pynxtools_igor-0.1.4.dist-info/METADATA
pynxtools_igor-0.1.4.dist-info/WHEEL
pynxtools_igor-0.1.4.dist-info/entry_points.txt
pynxtools_igor-0.1.4.dist-info/top_level.txt
pynxtools_igor-0.1.4.dist-info/RECORD
