Metadata-Version: 2.4
Name: pynxtools-igor
Version: 0.1.4
Summary: pynxtools plugin for reading igor pro waves and packed experiments
Author: The NOMAD Authors
License: Apache-2.0
Project-URL: Homepage, https://github.com/FAIRmat-NFDI/pynxtools-igor
Project-URL: Bug Tracker, https://github.com/FAIRmat-NFDI/pynxtools-igor/issues
Classifier: Programming Language :: Python :: 3.10
Classifier: Programming Language :: Python :: 3.11
Classifier: Programming Language :: Python :: 3.12
Classifier: Programming Language :: Python :: 3.13
Classifier: License :: OSI Approved :: Apache Software License
Classifier: Operating System :: OS Independent
Requires-Python: >=3.10
License-File: LICENSE
Requires-Dist: pynxtools>=0.12.0
Requires-Dist: igor2>=0.5.8
Provides-Extra: dev
Requires-Dist: mypy; extra == "dev"
Requires-Dist: ruff>=0.12.0; extra == "dev"
Requires-Dist: pytest; extra == "dev"
Requires-Dist: pytest-cov; extra == "dev"
Requires-Dist: types-pyyaml; extra == "dev"
Requires-Dist: pre-commit; extra == "dev"
Provides-Extra: docs
Requires-Dist: mkdocs; extra == "docs"
Requires-Dist: mkdocs-material; extra == "docs"
Requires-Dist: mkdocs-material-extensions; extra == "docs"
Requires-Dist: mkdocs-macros-plugin; extra == "docs"
Requires-Dist: pymdown-extensions; extra == "docs"
Requires-Dist: mkdocs-click; extra == "docs"
Dynamic: license-file
